avalanchepy/__init__.py
avalanchepy/contants.py
avalanchepy/clients/__init__.py
avalanchepy/clients/base_client.py
avalanchepy/clients/errors.py
avalanchepy/clients/info_client.py
avalanchepy/clients/p_client.py
avalanchepy/clients/x_client.py
avalanchepy/json_provider/__init__.py
avalanchepy/json_provider/errors.py
avalanchepy/json_provider/json_provider.py
avalanchepy/models/__init__.py
avalanchepy/models/info_models.py
avalanchepy/models/p_models.py
avalanchepy/models/x_models.py
avalanchepy/transaction_builder/__init__.py
avalanchepy/transaction_builder/errors.py
avalanchepy/transaction_builder/types.py
avalanchepy/transaction_builder/use_consolidate_output.py
avalanchepy/transaction_builder/use_spendable_locked_utxo.py
avalanchepy/transaction_builder/use_unlocked_utxo.py
avalanchepy/transaction_builder/utils.py
avalanchepy/types/__init__.py
avalanchepy/types/codecs.py
avalanchepy/types/errors.py
avalanchepy/types/seder.py
avalanchepy/types/signable.py
avalanchepy/types/utils.py
avalanchepy/types/avax/__init__.py
avalanchepy/types/avax/add_permissionless_delegator_tx.py
avalanchepy/types/avax/base_tx.py
avalanchepy/types/avax/credential.py
avalanchepy/types/avax/signed_tx.py
avalanchepy/types/avax/subnet_validator.py
avalanchepy/types/avax/utxo.py
avalanchepy/types/avax/utxoid.py
avalanchepy/types/avax/validator.py
avalanchepy/types/avax/inputs/secp256k1_signature.py
avalanchepy/types/avax/inputs/secp256k1_transfer_input.py
avalanchepy/types/avax/inputs/transferable_input.py
avalanchepy/types/avax/outputs/__init__.py
avalanchepy/types/avax/outputs/secp256k1_output_owners.py
avalanchepy/types/avax/outputs/secp256k1_transfer_output.py
avalanchepy/types/avax/outputs/stakeable_lock_out.py
avalanchepy/types/avax/outputs/transferable_output.py
avalanchepy/types/primitives/__init__.py
avalanchepy/types/primitives/address.py
avalanchepy/types/primitives/byte.py
avalanchepy/types/primitives/constants.py
avalanchepy/types/primitives/id.py
avalanchepy-0.1.0.dist-info/METADATA
avalanchepy-0.1.0.dist-info/WHEEL
avalanchepy-0.1.0.dist-info/top_level.txt
avalanchepy-0.1.0.dist-info/RECORD
