Metadata-Version: 2.4
Name: avalanchepy
Version: 0.1.0
Summary: Python library for interfacing with the Avalanche Platform
Author-email: Twinstake <info@twinstake.io>, Paco Edwin <edwinswatpako@gmail.com>
License-Expression: MIT
